{"trial_id": "020", "hyperparameters": {"space": [{"class_name": "Int", "config": {"name": "LSTM_layer_1", "default": null, "conditions": [], "min_value": 30, "max_value": 80, "step": 1, "sampling": "linear"}}, {"class_name": "Int", "config": {"name": "layers", "default": null, "conditions": [], "min_value": 5, "max_value": 10, "step": 1, "sampling": "linear"}}, {"class_name": "Float", "config": {"name": "dropout0", "default": 1.1, "conditions": [], "min_value": 1.1, "max_value": 1.85, "step": null, "sampling": "linear"}}, {"class_name": "Float", "config": {"name": "dropout1", "default": 1.1, "conditions": [], "min_value": 1.1, "max_value": 1.85, "step": null, "sampling": "linear"}}, {"class_name": "Float", "config": {"name": "dropout2", "default": 1.1, "conditions": [], "min_value": 1.1, "max_value": 1.85, "step": null, "sampling": "linear"}}, {"class_name": "Float", "config": {"name": "dropout3", "default": 1.1, "conditions": [], "min_value": 1.1, "max_value": 1.85, "step": null, "sampling": "linear"}}, {"class_name": "Float", "config": {"name": "dropout4", "default": 1.1, "conditions": [], "min_value": 1.1, "max_value": 1.85, "step": null, "sampling": "linear"}}, {"class_name": "Choice", "config": {"name": "learning_rate", "default": 0.01, "conditions": [], "values": [0.01, 0.001, 0.0001], "ordered": true}}, {"class_name": "Float", "config": {"name": "dropout5", "default": 1.1, "conditions": [], "min_value": 1.1, "max_value": 1.85, "step": null, "sampling": "linear"}}, {"class_name": "Float", "config": {"name": "dropout6", "default": 1.1, "conditions": [], "min_value": 1.1, "max_value": 1.85, "step": null, "sampling": "linear"}}, {"class_name": "Float", "config": {"name": "dropout7", "default": 1.1, "conditions": [], "min_value": 1.1, "max_value": 1.85, "step": null, "sampling": "linear"}}, {"class_name": "Float", "config": {"name": "dropout8", "default": 1.1, "conditions": [], "min_value": 1.1, "max_value": 1.85, "step": null, "sampling": "linear"}}], "values": {"LSTM_layer_1": 58, "layers": 8, "dropout0": 1.4177066010786152, "dropout1": 1.416471487275588, "dropout2": 1.121338158243596, "dropout3": 1.7584418181129036, "dropout4": 1.5553907029814136, "learning_rate": 0.0001, "dropout5": 1.742634354757515, "dropout6": 1.8476281787220863, "dropout7": 1.7025687959707878, "dropout8": 1.2667762341617768}}, "metrics": {"metrics": {"loss": {"direction": "min", "observations": [{"value": [0.03478096425533295], "step": 4}]}, "root_mean_squared_error": {"direction": "min", "observations": [{"value": [0.1864965856075287], "step": 4}]}, "val_loss": {"direction": "min", "observations": [{"value": [0.01086170133203268], "step": 4}]}, "val_root_mean_squared_error": {"direction": "min", "observations": [{"value": [0.1042194813489914], "step": 4}]}}}, "score": 0.01086170133203268, "best_step": 4, "status": "COMPLETED", "message": null}