{"trial_id": "034", "hyperparameters": {"space": [{"class_name": "Int", "config": {"name": "LSTM_layer_1", "default": null, "conditions": [], "min_value": 30, "max_value": 80, "step": 1, "sampling": "linear"}}, {"class_name": "Int", "config": {"name": "layers", "default": null, "conditions": [], "min_value": 5, "max_value": 10, "step": 1, "sampling": "linear"}}, {"class_name": "Float", "config": {"name": "dropout0", "default": 1.1, "conditions": [], "min_value": 1.1, "max_value": 1.85, "step": null, "sampling": "linear"}}, {"class_name": "Float", "config": {"name": "dropout1", "default": 1.1, "conditions": [], "min_value": 1.1, "max_value": 1.85, "step": null, "sampling": "linear"}}, {"class_name": "Float", "config": {"name": "dropout2", "default": 1.1, "conditions": [], "min_value": 1.1, "max_value": 1.85, "step": null, "sampling": "linear"}}, {"class_name": "Float", "config": {"name": "dropout3", "default": 1.1, "conditions": [], "min_value": 1.1, "max_value": 1.85, "step": null, "sampling": "linear"}}, {"class_name": "Float", "config": {"name": "dropout4", "default": 1.1, "conditions": [], "min_value": 1.1, "max_value": 1.85, "step": null, "sampling": "linear"}}, {"class_name": "Choice", "config": {"name": "learning_rate", "default": 0.01, "conditions": [], "values": [0.01, 0.001, 0.0001], "ordered": true}}, {"class_name": "Float", "config": {"name": "dropout5", "default": 1.1, "conditions": [], "min_value": 1.1, "max_value": 1.85, "step": null, "sampling": "linear"}}, {"class_name": "Float", "config": {"name": "dropout6", "default": 1.1, "conditions": [], "min_value": 1.1, "max_value": 1.85, "step": null, "sampling": "linear"}}, {"class_name": "Float", "config": {"name": "dropout7", "default": 1.1, "conditions": [], "min_value": 1.1, "max_value": 1.85, "step": null, "sampling": "linear"}}, {"class_name": "Float", "config": {"name": "dropout8", "default": 1.1, "conditions": [], "min_value": 1.1, "max_value": 1.85, "step": null, "sampling": "linear"}}, {"class_name": "Float", "config": {"name": "dropout9", "default": 1.1, "conditions": [], "min_value": 1.1, "max_value": 1.85, "step": null, "sampling": "linear"}}], "values": {"LSTM_layer_1": 31, "layers": 6, "dropout0": 1.2683188638126164, "dropout1": 1.5664226509089456, "dropout2": 1.1951725640314226, "dropout3": 1.4466971129600863, "dropout4": 1.1152925754498442, "learning_rate": 0.0001, "dropout5": 1.5705647758479273, "dropout6": 1.7122662263976993, "dropout7": 1.2339948306562447, "dropout8": 1.402963319845245, "dropout9": 1.622877810009974}}, "metrics": {"metrics": {"loss": {"direction": "min", "observations": [{"value": [0.012732141651213169], "step": 4}]}, "root_mean_squared_error": {"direction": "min", "observations": [{"value": [0.11283678561449051], "step": 4}]}, "val_loss": {"direction": "min", "observations": [{"value": [0.012375394813716412], "step": 4}]}, "val_root_mean_squared_error": {"direction": "min", "observations": [{"value": [0.11124475300312042], "step": 4}]}}}, "score": 0.012375394813716412, "best_step": 4, "status": "COMPLETED", "message": null}