{"trial_id": "111", "hyperparameters": {"space": [{"class_name": "Int", "config": {"name": "LSTM_layer_1", "default": null, "conditions": [], "min_value": 30, "max_value": 80, "step": 1, "sampling": "linear"}}, {"class_name": "Int", "config": {"name": "layers", "default": null, "conditions": [], "min_value": 5, "max_value": 10, "step": 1, "sampling": "linear"}}, {"class_name": "Float", "config": {"name": "dropout0", "default": 1.1, "conditions": [], "min_value": 1.1, "max_value": 1.85, "step": null, "sampling": "linear"}}, {"class_name": "Float", "config": {"name": "dropout1", "default": 1.1, "conditions": [], "min_value": 1.1, "max_value": 1.85, "step": null, "sampling": "linear"}}, {"class_name": "Float", "config": {"name": "dropout2", "default": 1.1, "conditions": [], "min_value": 1.1, "max_value": 1.85, "step": null, "sampling": "linear"}}, {"class_name": "Float", "config": {"name": "dropout3", "default": 1.1, "conditions": [], "min_value": 1.1, "max_value": 1.85, "step": null, "sampling": "linear"}}, {"class_name": "Float", "config": {"name": "dropout4", "default": 1.1, "conditions": [], "min_value": 1.1, "max_value": 1.85, "step": null, "sampling": "linear"}}, {"class_name": "Choice", "config": {"name": "learning_rate", "default": 0.01, "conditions": [], "values": [0.01, 0.001, 0.0001], "ordered": true}}, {"class_name": "Float", "config": {"name": "dropout5", "default": 1.1, "conditions": [], "min_value": 1.1, "max_value": 1.85, "step": null, "sampling": "linear"}}, {"class_name": "Float", "config": {"name": "dropout6", "default": 1.1, "conditions": [], "min_value": 1.1, "max_value": 1.85, "step": null, "sampling": "linear"}}, {"class_name": "Float", "config": {"name": "dropout7", "default": 1.1, "conditions": [], "min_value": 1.1, "max_value": 1.85, "step": null, "sampling": "linear"}}, {"class_name": "Float", "config": {"name": "dropout8", "default": 1.1, "conditions": [], "min_value": 1.1, "max_value": 1.85, "step": null, "sampling": "linear"}}, {"class_name": "Float", "config": {"name": "dropout9", "default": 1.1, "conditions": [], "min_value": 1.1, "max_value": 1.85, "step": null, "sampling": "linear"}}], "values": {"LSTM_layer_1": 41, "layers": 5, "dropout0": 1.1, "dropout1": 1.3870767023191402, "dropout2": 1.1, "dropout3": 1.485019331849923, "dropout4": 1.85, "learning_rate": 0.01, "dropout5": 1.85, "dropout6": 1.7103982793056787, "dropout7": 1.1, "dropout8": 1.108727873589575, "dropout9": 1.776476651816865}}, "metrics": {"metrics": {"loss": {"direction": "min", "observations": [{"value": [0.00377556006424129], "step": 3}]}, "root_mean_squared_error": {"direction": "min", "observations": [{"value": [0.06144557520747185], "step": 3}]}, "val_loss": {"direction": "min", "observations": [{"value": [0.0018335615750402212], "step": 3}]}, "val_root_mean_squared_error": {"direction": "min", "observations": [{"value": [0.04282010719180107], "step": 3}]}}}, "score": 0.0018335615750402212, "best_step": 3, "status": "COMPLETED", "message": null}