{"trial_id": "001", "hyperparameters": {"space": [{"class_name": "Int", "config": {"name": "LSTM_layer_1", "default": null, "conditions": [], "min_value": 30, "max_value": 80, "step": 1, "sampling": "linear"}}, {"class_name": "Int", "config": {"name": "layers", "default": null, "conditions": [], "min_value": 5, "max_value": 10, "step": 1, "sampling": "linear"}}, {"class_name": "Float", "config": {"name": "dropout0", "default": 1.1, "conditions": [], "min_value": 1.1, "max_value": 1.85, "step": null, "sampling": "linear"}}, {"class_name": "Float", "config": {"name": "dropout1", "default": 1.1, "conditions": [], "min_value": 1.1, "max_value": 1.85, "step": null, "sampling": "linear"}}, {"class_name": "Float", "config": {"name": "dropout2", "default": 1.1, "conditions": [], "min_value": 1.1, "max_value": 1.85, "step": null, "sampling": "linear"}}, {"class_name": "Float", "config": {"name": "dropout3", "default": 1.1, "conditions": [], "min_value": 1.1, "max_value": 1.85, "step": null, "sampling": "linear"}}, {"class_name": "Float", "config": {"name": "dropout4", "default": 1.1, "conditions": [], "min_value": 1.1, "max_value": 1.85, "step": null, "sampling": "linear"}}, {"class_name": "Choice", "config": {"name": "learning_rate", "default": 0.01, "conditions": [], "values": [0.01, 0.001, 0.0001], "ordered": true}}], "values": {"LSTM_layer_1": 41, "layers": 5, "dropout0": 1.345253670614414, "dropout1": 1.4729100205138024, "dropout2": 1.2889461895884626, "dropout3": 1.3510297969800071, "dropout4": 1.4340247761234428, "learning_rate": 0.0001}}, "metrics": {"metrics": {"loss": {"direction": "min", "observations": [{"value": [0.014167550019919872], "step": 4}]}, "root_mean_squared_error": {"direction": "min", "observations": [{"value": [0.1190275028347969], "step": 4}]}, "val_loss": {"direction": "min", "observations": [{"value": [0.00889358576387167], "step": 4}]}, "val_root_mean_squared_error": {"direction": "min", "observations": [{"value": [0.09430579841136932], "step": 4}]}}}, "score": 0.00889358576387167, "best_step": 4, "status": "COMPLETED", "message": null}